bioaxis/.gitignore
bioaxis/__init__.py
bioaxis/base/Draw.py
bioaxis/base/Touch.py
bioaxis/base/Transmitter.py
bioaxis/base/__init__.py
bioaxis/dataset/Splitter.py
bioaxis/dataset/__init__.py
bioaxis/dr.py
bioaxis/ds.py
bioaxis/util/DimensionReduction.py
bioaxis/util/__init__.py
bioaxis-0.1.0.dist-info/LICENSE
bioaxis-0.1.0.dist-info/METADATA
bioaxis-0.1.0.dist-info/WHEEL
bioaxis-0.1.0.dist-info/RECORD
