Metadata-Version: 2.3
Name: bioaxis
Version: 0.1.0
Summary: 
Author: Jianfeng Sun
Author-email: jianfeng.sunmt@gmail.com
Requires-Python: >=3.12
Classifier: Programming Language :: Python :: 3
Classifier: Programming Language :: Python :: 3.12
Classifier: Programming Language :: Python :: 3.13
Requires-Dist: matplotlib (>=3.10.3,<4.0.0)
Requires-Dist: seaborn (>=0.13.2,<0.14.0)
